{
  "gitSyncId": "3c4e1923-f057-41c3-99e8-5eea5d73bf1d_37538ced-335c-47cd-ab80-97f3b49bfc6d",
  "id": "JSModuleOne_JSModuleOne.getUsers",
  "isPublic": true,
  "pluginId": "js-plugin",
  "pluginType": "JS",
  "unpublishedAction": {
    "actionConfiguration": {
      "encodeParamsToggle": true,
      "jsArguments": [
        {
          "name": "limit",
          "value": "{{1}}"
        }
      ],
      "paginationType": "NONE",
      "timeoutInMillisecond": 10000
    },
    "clientSideExecution": true,
    "collectionId": "JSModuleOne_JSModuleOne",
    "confirmBeforeExecute": false,
    "contextType": "MODULE",
    "datasource": {
      "isAutoGenerated": false,
      "name": "UNUSED_DATASOURCE",
      "pluginId": "js-plugin"
    },
    "dynamicBindingPathList": [
      {
        "key": "body"
      }
    ],
    "executeOnLoad": false,
    "fullyQualifiedName": "JSModuleOne.getUsers",
    "moduleId": "JSModuleOne",
    "name": "getUsers",
    "userSetOnLoad": false
  }
}